Clock Divider/ClkDiv.v
/********************************************************************************************/
/********************************************************************************************/
/**************************		Author: Alyaa Mohamed    ************************************/
/**************************		Module: ClkDiv	         ************************************/
/********************************************************************************************/
/********************************************************************************************/

module ClkDiv #(parameter WIDTH = 3)
(
    input   wire                    i_ref_clk                                       ,
    input   wire                    i_rst_n                                         ,
    input   wire                    i_clk_en                                        ,
    input   wire  [WIDTH-1:0]       i_div_ratio                                     ,

    output  wire                    o_div_clk
);

/*****************************************************************************************/
/*****************************************************************************************/

    reg           [WIDTH-1:0]       counter                                         ;
    reg                             clk_div                                         ;

/*****************************************************************************************/
/*****************************************************************************************/

    always@(posedge i_ref_clk or negedge i_rst_n)
        begin
            if(!i_rst_n)

                counter   <= 'b0                                                    ;

            else if(i_clk_en)
            
                counter <= (counter == (i_div_ratio-1) ) ? 'b0 : (counter + 'b1)    ;
        
        end

/*****************************************************************************************/
/*****************************************************************************************/

    always @(posedge i_ref_clk or negedge i_rst_n)
        begin

            if(!i_rst_n)
             
                clk_div <= 'b0                                                      ;
            
            else if(i_clk_en)
                    
                clk_div <= (counter < (i_div_ratio/2) ) ?  1'b1 : 1'b0              ; 

        end
   
/*****************************************************************************************/
/*****************************************************************************************/

    assign o_div_clk = (i_clk_en) ? clk_div : i_ref_clk                             ;
    
endmodule

Clock Divider/ClkDiv_tb.v
/********************************************************************************************/
/********************************************************************************************/
/**************************		Author: Alyaa Mohamed    ************************************/
/**************************		Module: ClkDiv_tb	     ************************************/
/********************************************************************************************/
/********************************************************************************************/

`timescale 1ns/1ps

module ClkDiv_tb();

    parameter               WIDTH_tb        = 3                         ;

/*****************************************************************************************/
/*****************************************************************************************/

    reg                     i_ref_clk_tb                                ;
    reg                     i_rst_n_tb                                  ;
    reg                     i_clk_en_tb                                 ;
    reg  [WIDTH_tb-1:0]     i_div_ratio_tb                              ;

    wire                     o_div_clk_tb                               ;

/*****************************************************************************************/
/*****************************************************************************************/

    localparam              CLK_PERIOD      = 100                       ;

/*****************************************************************************************/
/*****************************************************************************************/

    initial
        begin
            
            $dumpfile("ClkDiv_tb.vcd") 				                    ;
            $dumpvars 									                ;

            i_ref_clk_tb    = 'b0                                       ;
            i_rst_n_tb      = 'b0                                       ;
            i_clk_en_tb     = 'b0                                       ;
            i_div_ratio_tb  = 'b0                                       ;

/*****************************************************************************************/
/*****************************************************************************************/

            $monitor("Ref clk=%b,Div clk=%b",i_ref_clk_tb,o_div_clk_tb) ;

/*****************************************************************************************/
/*****************************************************************************************/

            #CLK_PERIOD
            i_rst_n_tb      = 'b1                                       ;
            i_div_ratio_tb  = 'b100                                     ;

            #(CLK_PERIOD*3)
            i_clk_en_tb     = 'b1                                       ;

/*****************************************************************************************/
/*****************************************************************************************/

            $display ("\n\nDivision by 4\n\n");
            #(CLK_PERIOD*8)

/*****************************************************************************************/
/*****************************************************************************************/

            i_rst_n_tb      = 'b0                                       ;
            i_div_ratio_tb  = 'b101                                     ;        

            #CLK_PERIOD
            i_rst_n_tb      = 'b1                                       ;

/*****************************************************************************************/
/*****************************************************************************************/

            $display ("\n\nDivision by 5\n\n")                          ;
            #(CLK_PERIOD*8)

            $finish	                                                    ;

            end

/*****************************************************************************************/
/*****************************************************************************************/

    always #(CLK_PERIOD*0.5) i_ref_clk_tb = !i_ref_clk_tb			    ;

/*****************************************************************************************/
/*****************************************************************************************/

    ClkDiv #(.WIDTH(WIDTH_tb))
    DUT
    (
        .i_ref_clk(i_ref_clk_tb)                                        ,
        .i_rst_n(i_rst_n_tb)                                            ,
        .i_clk_en(i_clk_en_tb)                                          ,
        .i_div_ratio(i_div_ratio_tb)                                    ,

        .o_div_clk(o_div_clk_tb)
    );

endmodule

Clock Divider/ClkDiv_tb.vcd
$date
	Sun Aug 07 16:51:43 2022
$end
$version
	ModelSim Version 10.5b
$end
$timescale
	1ps
$end

$scope module ClkDiv_tb $end
$var parameter 32 ! WIDTH_tb $end
$var parameter 32 " CLK_PERIOD $end
$var reg 1 # i_ref_clk_tb $end
$var reg 1 $ i_rst_n_tb $end
$var reg 1 % i_clk_en_tb $end
$var reg 3 & i_div_ratio_tb [2:0] $end
$var wire 1 ' o_div_clk_tb $end

$scope module DUT $end
$var parameter 32 ( WIDTH $end
$var wire 1 ) i_ref_clk $end
$var wire 1 * i_rst_n $end
$var wire 1 + i_clk_en $end
$var wire 1 , i_div_ratio [2] $end
$var wire 1 - i_div_ratio [1] $end
$var wire 1 . i_div_ratio [0] $end
$var wire 1 ' o_div_clk $end
$var reg 3 / counter [2:0] $end
$var reg 1 0 clk_div $end
$upscope $end
$upscope $end
$enddefinitions $end
#0
$dumpvars
0#
0$
0%
b0 &
b0 /
00
b11 !
b1100100 "
b11 (
0'
0.
0-
0,
0+
0*
0)
$end
#50000
1#
1)
1'
#100000
1$
b100 &
0#
1,
1*
0)
0'
#150000
1#
1)
1'
#200000
0#
0)
0'
#250000
1#
1)
1'
#300000
0#
0)
0'
#350000
1#
1)
1'
#400000
1%
0#
1+
0'
0)
#450000
1#
1)
b1 /
10
1'
#500000
0#
0)
#550000
1#
1)
b10 /
#600000
0#
0)
#650000
1#
1)
b11 /
00
0'
#700000
0#
0)
#750000
1#
1)
b0 /
#800000
0#
0)
#850000
1#
1)
b1 /
10
1'
#900000
0#
0)
#950000
1#
1)
b10 /
#1000000
0#
0)
#1050000
1#
1)
b11 /
00
0'
#1100000
0#
0)
#1150000
1#
1)
b0 /
#1200000
0$
b101 &
0#
1.
0*
0)
#1250000
1#
1)
#1300000
1$
0#
1*
0)
#1350000
1#
1)
b1 /
10
1'
#1400000
0#
0)
#1450000
1#
1)
b10 /
#1500000
0#
0)
#1550000
1#
1)
b11 /
00
0'
#1600000
0#
0)
#1650000
1#
1)
b100 /
#1700000
0#
0)
#1750000
1#
1)
b0 /
#1800000
0#
0)
#1850000
1#
1)
b1 /
10
1'
#1900000
0#
0)
#1950000
1#
1)
b10 /
#2000000
0#
0)
#2050000
1#
1)
b11 /
00
0'
