RST_Sync/RST_Sync.v
module RST_Sync #(parameter NUM_STAGES = 2)
(
    input   wire                    RST                                 ,
    input   wire                    CLK                                 ,

    output  reg                     Sync_RST    
);

/********************************************************************************/
/********************************************************************************/

    reg          [NUM_STAGES-1:0]   register                            ;

/********************************************************************************/
/********************************************************************************/

    always @(posedge CLK or negedge RST) 
        begin

            if(!RST)
                begin

                    register <= 'b0                                     ;
                    Sync_RST <= 'b0                                     ; 
                
                end
            else
            
                {Sync_RST,register} <= {register[NUM_STAGES-1:0],1'b1}  ;

        end

endmodule

RST_Sync/RST_Sync_tb.v
`timescale 1ns/1ps

module RST_Sync_tb()                                            ;

    parameter 				NUM_STAGES_tb   = 2 			    ;

/********************************************************************************/
/********************************************************************************/


    reg                     RST_tb                              ;
    reg                     CLK_tb                              ;

    wire                    Sync_RST_tb                         ;

/********************************************************************************/
/********************************************************************************/

    localparam              CLK_PERIOD      = 100               ;

/********************************************************************************/
/********************************************************************************/

    initial
        begin
        
            $dumpfile("RST_Sync_tb.vcd") 				        ;
            $dumpvars 									        ;

            CLK_tb = 'b0                                        ;

/********************************************************************************/
/********************************************************************************/

            RST_tb = 1'b1                                       ;
            #(CLK_PERIOD*3) 

            $display ("\n\nTEST CASE 0")				        ;

            if (Sync_RST_tb == 1 )
            
                $display ("\nPassed\n")					        ;

            else
                
                $display ("\nFailed\n")					        ;


/********************************************************************************/
/********************************************************************************/

            #(CLK_PERIOD*0.7)
            RST_tb = 1'b0                                       ;

            #(CLK_PERIOD*0.4)
            RST_tb = 1'b1                                       ;

            #(CLK_PERIOD*0.9)
            $display ("\n\nTEST CASE 1")				        ;

            if (Sync_RST_tb == 0 )
            
                $display ("\nPassed\n")					        ;

            else
                
                $display ("\nFailed\n")					        ;

/********************************************************************************/
/********************************************************************************/

            #(CLK_PERIOD*2) 

            $display ("\n\nTEST CASE 2")				        ;

            if (Sync_RST_tb == 1 )
            
                $display ("\nPassed\n")					        ;

            else
                
                $display ("\nFailed\n")					        ;    

            #(CLK_PERIOD*10)
            $finish										        ;
        end

/********************************************************************************/
/********************************************************************************/

    always #(CLK_PERIOD*0.5) CLK_tb = !CLK_tb			        ;

/********************************************************************************/
/********************************************************************************/

    RST_Sync #(.NUM_STAGES(NUM_STAGES_tb))
    DUT
    (
        .RST(RST_tb)                                            ,
        .CLK(CLK_tb)                                            ,

        .Sync_RST(Sync_RST_tb)    
    );

endmodule

RST_Sync/RST_Sync_tb.vcd
$date
	Thu Jul 21 20:28:33 2022
$end
$version
	ModelSim Version 10.5b
$end
$timescale
	1ps
$end

$scope module RST_Sync_tb $end
$var parameter 32 ! NUM_STAGES_tb $end
$var parameter 32 " CLK_PERIOD $end
$var reg 1 # RST_tb $end
$var reg 1 $ CLK_tb $end
$var wire 1 % Sync_RST_tb $end

$scope module DUT $end
$var parameter 32 & NUM_STAGES $end
$var wire 1 ' RST $end
$var wire 1 ( CLK $end
$var reg 1 ) Sync_RST $end
$var reg 2 * register [1:0] $end
$upscope $end
$upscope $end
$enddefinitions $end
#0
$dumpvars
1#
0$
x)
bx *
b10 !
b1100100 "
b10 &
x%
0(
1'
$end
#50000
1$
1(
bx1 *
#100000
0$
0(
#150000
1$
1(
b11 *
#200000
0$
0(
#250000
1$
1(
1)
1%
#300000
0$
0(
#350000
1$
1(
#370000
0#
0'
b0 *
0)
0%
#400000
0$
0(
#410000
1#
1'
#450000
1$
1(
b1 *
#500000
0$
0(
#550000
1$
1(
b11 *
#600000
0$
0(
#650000
1$
1(
1)
1%
